alnmeshpy/__init__.py
alnmeshpy/ble_channel.py
alnmeshpy/ble_scan.py
alnmeshpy/ble_serial.py
alnmeshpy/bt_channel.py
alnmeshpy/frame.py
alnmeshpy/local_channel.py
alnmeshpy/packet.py
alnmeshpy/parser.py
alnmeshpy/router.py
alnmeshpy/tcp_channel.py
alnmeshpy/tcp_host.py
alnmeshpy-0.1.0.dist-info/METADATA
alnmeshpy-0.1.0.dist-info/WHEEL
alnmeshpy-0.1.0.dist-info/licenses/LICENSE
alnmeshpy-0.1.0.dist-info/RECORD
