Metadata-Version: 2.4
Name: alnmeshpy
Version: 0.1.0
Summary: An implementation of the Application Layer Network (ALN).
Project-URL: GitHub, https://github.com/chadbohannan/application-layer-network
Project-URL: Issues, https://github.com/chadbohannan/application-layer-network/issues
Project-URL: Homepage, https://biglittleidea.org/article/5706803308396544
Author-email: Chad Bohannan <chadbohannan@biglittleidea.org>
License-File: LICENSE
Classifier: License :: OSI Approved :: MIT License
Classifier: Operating System :: OS Independent
Classifier: Programming Language :: Python :: 3
Requires-Python: >=3.8
Requires-Dist: aiofiles>=24.1.0
Provides-Extra: dev
Requires-Dist: pip>=25.0.1; extra == 'dev'
Requires-Dist: pytest>=8.2.2; extra == 'dev'
